odoo/addons/purchase_partner_incoterm/README.rst
odoo/addons/purchase_partner_incoterm/__init__.py
odoo/addons/purchase_partner_incoterm/__manifest__.py
odoo/addons/purchase_partner_incoterm/i18n/fr.po
odoo/addons/purchase_partner_incoterm/i18n/fr_1.po
odoo/addons/purchase_partner_incoterm/i18n/it.po
odoo/addons/purchase_partner_incoterm/i18n/pt_BR.po
odoo/addons/purchase_partner_incoterm/i18n/purchase_partner_incoterm.pot
odoo/addons/purchase_partner_incoterm/i18n/sl.po
odoo/addons/purchase_partner_incoterm/models/__init__.py
odoo/addons/purchase_partner_incoterm/models/purchase_order.py
odoo/addons/purchase_partner_incoterm/models/res_partner.py
odoo/addons/purchase_partner_incoterm/readme/CONTRIBUTORS.md
odoo/addons/purchase_partner_incoterm/readme/CREDITS.md
odoo/addons/purchase_partner_incoterm/readme/DESCRIPTION.md
odoo/addons/purchase_partner_incoterm/static/description/icon.png
odoo/addons/purchase_partner_incoterm/static/description/index.html
odoo/addons/purchase_partner_incoterm/tests/__init__.py
odoo/addons/purchase_partner_incoterm/tests/test_purchase_partner_incoterm.py
odoo/addons/purchase_partner_incoterm/views/partner_view.xml
odoo/addons/purchase_partner_incoterm/views/purchase_view.xml
odoo_addon_purchase_partner_incoterm-18.0.1.0.1.2.dist-info/METADATA
odoo_addon_purchase_partner_incoterm-18.0.1.0.1.2.dist-info/WHEEL
odoo_addon_purchase_partner_incoterm-18.0.1.0.1.2.dist-info/top_level.txt
odoo_addon_purchase_partner_incoterm-18.0.1.0.1.2.dist-info/RECORD
